2to1mux.v
module mux(out, a, b, ctrl);
	output out;
	input a, b, ctrl;
	wire ctrlBar, w1, w2;
	not not1(ctrlBar, ctrl);
	and and1(w1, ctrlBar, a);
	and and2(w2, ctrl, b);
	or or1(out, w1, w2);
endmodule

sr_latch.v
module sr_latch(q, qbar, s, r);

input r, s;
output q, qbar;
nor nor1(q, r, qbar);
nor nor2(qbar, s, q);

endmodule

r_d_latch.v
module r_d_latch(out, d, clock, reset);
	output out;
	input d, clock, reset;
	wire dBar, preR, preS, qBar;
	reg reset1, set0;
	initial reset1 = 1;
       	initial	set0 = 0;
	not not1(dBar, d);
	and and1(preR, dBar, clock);
	and and2(preS, d, clock);
	mux mux1(r, preR,reset1, reset);
	mux mux2(s, preS, set0, reset);
	sr_latch main(out,qBar , s, r);
endmodule

r_d_flipflop.v
module r_d_flipflop(out, in, clock, reset);
	input in, clock, reset;
	output out;
	wire clockBar, in2slave;
	not not1(clockBar, clock);
	r_d_latch master(in2slave, in, clockBar, reset);
	r_d_latch slave(out, in2slave, clock, reset);

endmodule

r_t_flipflop.v
module r_t_flipflop(out, clock, reset);
	output out;
	input reset, clock;
	wire outBar;
	not not1(outBar, out);
	r_d_flipflop main(out, outBar, clock, reset);
endmodule

r_3_bit_counter.v
module r_3_bit_counter(out0, out1, out2, clock, reset);
	input clock, reset;
	output out0, out1, out2;
	r_t_flipflop main0(out0, clock, reset);
	r_t_flipflop main1(out1, out0, reset);
	r_t_flipflop main2(out2, out1, reset);
endmodule

test_2to1mux.v
`timescale 10ns/1ps

module testbench();
	reg clock, reset;
	wire out, a, b, ctrl;
	r_3_bit_counter counter(a, b, ctrl, clock, reset);
	initial clock = 0;
	always #10 clock = ~clock;
	initial reset = 0;
	mux dut(out, a, b, ctrl);
	initial begin
		$dumpfile("test_2to1mux.vcd");
		$dumpvars;
		reset = 1;
		#10;
		reset = 0;
	end
endmodule

test_2to1mux.vcd
$date
	Thu Mar 21 10:58:57 2019
$end
$version
	Icarus Verilog
$end
$timescale
	1ps
$end
$scope module testbench $end
$var wire 1 ! out $end
$var wire 1 " ctrl $end
$var wire 1 # b $end
$var wire 1 $ a $end
$var reg 1 % clock $end
$var reg 1 & reset $end
$scope module counter $end
$var wire 1 % clock $end
$var wire 1 & reset $end
$var wire 1 " out2 $end
$var wire 1 # out1 $end
$var wire 1 $ out0 $end
$scope module main0 $end
$var wire 1 % clock $end
$var wire 1 ' outBar $end
$var wire 1 & reset $end
$var wire 1 $ out $end
$scope module main $end
$var wire 1 % clock $end
$var wire 1 ( clockBar $end
$var wire 1 ' in $end
$var wire 1 & reset $end
$var wire 1 $ out $end
$var wire 1 ) in2slave $end
$scope module master $end
$var wire 1 ( clock $end
$var wire 1 ' d $end
$var wire 1 * dBar $end
$var wire 1 + preR $end
$var wire 1 , preS $end
$var wire 1 & reset $end
$var wire 1 - s $end
$var wire 1 . r $end
$var wire 1 / qBar $end
$var wire 1 ) out $end
$var reg 1 0 reset1 $end
$var reg 1 1 set0 $end
$scope module main $end
$var wire 1 ) q $end
$var wire 1 / qbar $end
$var wire 1 - s $end
$var wire 1 . r $end
$upscope $end
$scope module mux1 $end
$var wire 1 + a $end
$var wire 1 0 b $end
$var wire 1 & ctrl $end
$var wire 1 2 ctrlBar $end
$var wire 1 . out $end
$var wire 1 3 w1 $end
$var wire 1 4 w2 $end
$upscope $end
$scope module mux2 $end
$var wire 1 , a $end
$var wire 1 1 b $end
$var wire 1 & ctrl $end
$var wire 1 5 ctrlBar $end
$var wire 1 - out $end
$var wire 1 6 w1 $end
$var wire 1 7 w2 $end
$upscope $end
$upscope $end
$scope module slave $end
$var wire 1 % clock $end
$var wire 1 ) d $end
$var wire 1 8 dBar $end
$var wire 1 9 preR $end
$var wire 1 : preS $end
$var wire 1 & reset $end
$var wire 1 ; s $end
$var wire 1 < r $end
$var wire 1 = qBar $end
$var wire 1 $ out $end
$var reg 1 > reset1 $end
$var reg 1 ? set0 $end
$scope module main $end
$var wire 1 $ q $end
$var wire 1 = qbar $end
$var wire 1 ; s $end
$var wire 1 < r $end
$upscope $end
$scope module mux1 $end
$var wire 1 9 a $end
$var wire 1 > b $end
$var wire 1 & ctrl $end
$var wire 1 @ ctrlBar $end
$var wire 1 < out $end
$var wire 1 A w1 $end
$var wire 1 B w2 $end
$upscope $end
$scope module mux2 $end
$var wire 1 : a $end
$var wire 1 ? b $end
$var wire 1 & ctrl $end
$var wire 1 C ctrlBar $end
$var wire 1 ; out $end
$var wire 1 D w1 $end
$var wire 1 E w2 $end
$upscope $end
$upscope $end
$upscope $end
$upscope $end
$scope module main1 $end
$var wire 1 $ clock $end
$var wire 1 F outBar $end
$var wire 1 & reset $end
$var wire 1 # out $end
$scope module main $end
$var wire 1 $ clock $end
$var wire 1 G clockBar $end
$var wire 1 F in $end
$var wire 1 & reset $end
$var wire 1 # out $end
$var wire 1 H in2slave $end
$scope module master $end
$var wire 1 G clock $end
$var wire 1 F d $end
$var wire 1 I dBar $end
$var wire 1 J preR $end
$var wire 1 K preS $end
$var wire 1 & reset $end
$var wire 1 L s $end
$var wire 1 M r $end
$var wire 1 N qBar $end
$var wire 1 H out $end
$var reg 1 O reset1 $end
$var reg 1 P set0 $end
$scope module main $end
$var wire 1 H q $end
$var wire 1 N qbar $end
$var wire 1 L s $end
$var wire 1 M r $end
$upscope $end
$scope module mux1 $end
$var wire 1 J a $end
$var wire 1 O b $end
$var wire 1 & ctrl $end
$var wire 1 Q ctrlBar $end
$var wire 1 M out $end
$var wire 1 R w1 $end
$var wire 1 S w2 $end
$upscope $end
$scope module mux2 $end
$var wire 1 K a $end
$var wire 1 P b $end
$var wire 1 & ctrl $end
$var wire 1 T ctrlBar $end
$var wire 1 L out $end
$var wire 1 U w1 $end
$var wire 1 V w2 $end
$upscope $end
$upscope $end
$scope module slave $end
$var wire 1 $ clock $end
$var wire 1 H d $end
$var wire 1 W dBar $end
$var wire 1 X preR $end
$var wire 1 Y preS $end
$var wire 1 & reset $end
$var wire 1 Z s $end
$var wire 1 [ r $end
$var wire 1 \ qBar $end
$var wire 1 # out $end
$var reg 1 ] reset1 $end
$var reg 1 ^ set0 $end
$scope module main $end
$var wire 1 # q $end
$var wire 1 \ qbar $end
$var wire 1 Z s $end
$var wire 1 [ r $end
$upscope $end
$scope module mux1 $end
$var wire 1 X a $end
$var wire 1 ] b $end
$var wire 1 & ctrl $end
$var wire 1 _ ctrlBar $end
$var wire 1 [ out $end
$var wire 1 ` w1 $end
$var wire 1 a w2 $end
$upscope $end
$scope module mux2 $end
$var wire 1 Y a $end
$var wire 1 ^ b $end
$var wire 1 & ctrl $end
$var wire 1 b ctrlBar $end
$var wire 1 Z out $end
$var wire 1 c w1 $end
$var wire 1 d w2 $end
$upscope $end
$upscope $end
$upscope $end
$upscope $end
$scope module main2 $end
$var wire 1 # clock $end
$var wire 1 e outBar $end
$var wire 1 & reset $end
$var wire 1 " out $end
$scope module main $end
$var wire 1 # clock $end
$var wire 1 f clockBar $end
$var wire 1 e in $end
$var wire 1 & reset $end
$var wire 1 " out $end
$var wire 1 g in2slave $end
$scope module master $end
$var wire 1 f clock $end
$var wire 1 e d $end
$var wire 1 h dBar $end
$var wire 1 i preR $end
$var wire 1 j preS $end
$var wire 1 & reset $end
$var wire 1 k s $end
$var wire 1 l r $end
$var wire 1 m qBar $end
$var wire 1 g out $end
$var reg 1 n reset1 $end
$var reg 1 o set0 $end
$scope module main $end
$var wire 1 g q $end
$var wire 1 m qbar $end
$var wire 1 k s $end
$var wire 1 l r $end
$upscope $end
$scope module mux1 $end
$var wire 1 i a $end
$var wire 1 n b $end
$var wire 1 & ctrl $end
$var wire 1 p ctrlBar $end
$var wire 1 l out $end
$var wire 1 q w1 $end
$var wire 1 r w2 $end
$upscope $end
$scope module mux2 $end
$var wire 1 j a $end
$var wire 1 o b $end
$var wire 1 & ctrl $end
$var wire 1 s ctrlBar $end
$var wire 1 k out $end
$var wire 1 t w1 $end
$var wire 1 u w2 $end
$upscope $end
$upscope $end
$scope module slave $end
$var wire 1 # clock $end
$var wire 1 g d $end
$var wire 1 v dBar $end
$var wire 1 w preR $end
$var wire 1 x preS $end
$var wire 1 & reset $end
$var wire 1 y s $end
$var wire 1 z r $end
$var wire 1 { qBar $end
$var wire 1 " out $end
$var reg 1 | reset1 $end
$var reg 1 } set0 $end
$scope module main $end
$var wire 1 " q $end
$var wire 1 { qbar $end
$var wire 1 y s $end
$var wire 1 z r $end
$upscope $end
$scope module mux1 $end
$var wire 1 w a $end
$var wire 1 | b $end
$var wire 1 & ctrl $end
$var wire 1 ~ ctrlBar $end
$var wire 1 z out $end
$var wire 1 !" w1 $end
$var wire 1 "" w2 $end
$upscope $end
$scope module mux2 $end
$var wire 1 x a $end
$var wire 1 } b $end
$var wire 1 & ctrl $end
$var wire 1 #" ctrlBar $end
$var wire 1 y out $end
$var wire 1 $" w1 $end
$var wire 1 %" w2 $end
$upscope $end
$upscope $end
$upscope $end
$upscope $end
$upscope $end
$scope module dut $end
$var wire 1 $ a $end
$var wire 1 # b $end
$var wire 1 " ctrl $end
$var wire 1 &" ctrlBar $end
$var wire 1 ! out $end
$var wire 1 '" w1 $end
$var wire 1 (" w2 $end
$upscope $end
$upscope $end
$enddefinitions $end
#0
$dumpvars
0("
0'"
1&"
0%"
0$"
0#"
1""
0!"
0~
0}
1|
1{
1z
0y
0x
0w
1v
0u
0t
0s
1r
0q
0p
0o
1n
1m
1l
0k
1j
0i
0h
0g
1f
1e
0d
0c
0b
1a
0`
0_
0^
1]
1\
1[
0Z
0Y
0X
1W
0V
0U
0T
1S
0R
0Q
0P
1O
1N
1M
0L
1K
0J
0I
0H
1G
1F
0E
0D
0C
1B
0A
0@
0?
1>
1=
1<
0;
0:
09
18
07
06
05
14
03
02
01
10
1/
1.
0-
1,
0+
0*
0)
1(
1'
1&
0%
0$
0#
0"
0!
$end
#100000
0W
0v
1H
1g
0N
0m
1L
1k
0.
0M
1U
0[
0l
1t
0z
0,
1A
12
04
15
1@
0B
1C
1Q
0S
1T
1_
0a
1b
1p
0r
1s
1~
0""
1#"
0(
19
0&
1%
#200000
08
1)
0/
1-
16
0<
1,
0A
1(
09
0%
#300000
1h
0&"
1("
0e
1"
0k
0{
0t
1y
0j
1$"
1I
0f
1x
0F
1#
0L
0\
0U
1Z
0K
1c
1!
1*
0G
1Y
0'"
0'
1$
0-
0=
06
1;
0,
1D
0(
1:
1%
#400000
1/
18
0)
1.
13
0;
1+
0D
1(
0:
0%
#500000
1N
1W
0H
1M
1R
0Z
1J
0c
0*
1=
1G
0Y
1'
0.
0$
03
1<
0+
1A
0(
19
1%
#600000
08
1)
0/
1-
16
0<
1,
0A
1(
09
0%
#700000
1m
1v
0g
1l
1q
0y
1i
0$"
0!
0I
1\
1f
0x
0("
1F
0M
0#
0R
1[
0J
1`
1*
0G
1X
0'
1$
0-
0=
06
1;
0,
1D
0(
1:
1%
#800000
1/
18
0)
1.
13
0;
1+
0D
1(
0:
0%
#900000
0W
1H
0N
1L
1U
0[
1K
0`
0*
1=
1G
0X
1'
0.
0$
03
1<
0+
1A
0(
19
1%
#1000000
08
1)
0/
1-
16
0<
1,
0A
1(
09
0%
#1100000
1'"
0h
1{
1&"
1e
0l
0"
0q
1z
0i
1!"
1!
1I
0f
1w
0("
0F
1#
0L
0\
0U
1Z
0K
1c
1*
0G
1Y
0'
1$
0-
0=
06
1;
0,
1D
0(
1:
1%
#1200000
1/
18
0)
1.
13
0;
1+
0D
1(
0:
0%
#1300000
1N
1W
0H
1M
1R
0Z
1J
0c
0!
0*
1=
1G
0Y
0'"
1'
0.
0$
03
1<
0+
1A
0(
19
1%
#1400000
08
1)
0/
1-
16
0<
1,
0A
1(
09
0%
#1500000
0v
1g
0m
1k
1t
0z
1j
0!"
0I
1\
1f
0w
1F
0M
0#
0R
1[
0J
1`
1!
1*
0G
1X
1'"
0'
1$
0-
0=
06
1;
0,
1D
0(
1:
1%
#1600000
1/
18
0)
1.
13
0;
1+
0D
1(
0:
0%
#1700000
0W
1H
0N
1L
1U
0[
1K
0`
0!
0*
1=
1G
0X
0'"
1'
0.
0$
03
1<
0+
1A
0(
19
1%
#1800000
08
1)
0/
1-
16
0<
1,
0A
1(
09
0%
#1900000
1h
0&"
1("
0e
1"
0k
0{
0t
1y
0j
1$"
1I
0f
1x
0F
1#
0L
0\
0U
1Z
0K
1c
1!
1*
0G
1Y
0'"
0'
1$
0-
0=
06
1;
0,
1D
0(
1:
1%
#2000000
1/
18
0)
1.
13
0;
1+
0D
1(
0:
0%
#2100000
1N
1W
0H
1M
1R
0Z
1J
0c
0*
1=
1G
0Y
1'
0.
0$
03
1<
0+
1A
0(
19
1%
#2200000
08
1)
0/
1-
16
0<
1,
0A
1(
09
0%
#2300000
1m
1v
0g
1l
1q
0y
1i
0$"
0!
0I
1\
1f
0x
0("
1F
0M
0#
0R
1[
0J
1`
1*
0G
1X
0'
1$
0-
0=
06
1;
0,
1D
0(
1:
1%
#2400000
1/
18
0)
1.
13
0;
1+
0D
1(
0:
0%
#2500000
0W
1H
0N
1L
1U
0[
1K
0`
0*
1=
1G
0X
1'
0.
0$
03
1<
0+
1A
0(
19
1%
#2600000
08
1)
0/
1-
16
0<
1,
0A
1(
09
0%
#2700000
1'"
0h
1{
1&"
1e
0l
0"
0q
1z
0i
1!"
1!
1I
0f
1w
0("
0F
1#
0L
0\
0U
1Z
0K
1c
1*
0G
1Y
0'
1$
0-
0=
06
1;
0,
1D
0(
1:
1%
#2800000
1/
18
0)
1.
13
0;
1+
0D
1(
0:
0%
#2900000
1N
1W
0H
1M
1R
0Z
1J
0c
0!
0*
1=
1G
0Y
0'"
1'
0.
0$
03
1<
0+
1A
0(
19
1%
#3000000
08
1)
0/
1-
16
0<
1,
0A
1(
09
0%
#3100000
0v
1g
0m
1k
1t
0z
1j
0!"
0I
1\
1f
0w
1F
0M
0#
0R
1[
0J
1`
1!
1*
0G
1X
1'"
0'
1$
0-
0=
06
1;
0,
1D
0(
1:
1%
#3200000
1/
18
0)
1.
13
0;
1+
0D
1(
0:
0%
#3300000
0W
1H
0N
1L
1U
0[
1K
0`
0!
0*
1=
1G
0X
0'"
1'
0.
0$
03
1<
0+
1A
0(
19
1%
#3400000
08
1)
0/
1-
16
0<
1,
0A
1(
09
0%
#3500000
1h
0&"
1("
0e
1"
0k
0{
0t
1y
0j
1$"
1I
0f
1x
0F
1#
0L
0\
0U
1Z
0K
1c
1!
1*
0G
1Y
0'"
0'
1$
0-
0=
06
1;
0,
1D
0(
1:
1%
#3600000
1/
18
0)
1.
13
0;
1+
0D
1(
0:
0%
#3700000
1N
1W
0H
1M
1R
0Z
1J
0c
0*
1=
1G
0Y
1'
0.
0$
03
1<
0+
1A
0(
19
1%
#3800000
08
1)
0/
1-
16
0<
1,
0A
1(
09
0%
#3900000
1m
1v
0g
1l
1q
0y
1i
0$"
0!
0I
1\
1f
0x
0("
1F
0M
0#
0R
1[
0J
1`
1*
0G
1X
0'
1$
0-
0=
06
1;
0,
1D
0(
1:
1%
#4000000
1/
18
0)
1.
13
0;
1+
0D
1(
0:
0%
#4100000
0W
1H
0N
1L
1U
0[
1K
0`
0*
1=
1G
0X
1'
0.
0$
03
1<
0+
1A
0(
19
1%
#4200000
08
1)
0/
1-
16
0<
1,
0A
1(
09
0%
#4300000
1'"
0h
1{
1&"
1e
0l
0"
0q
1z
0i
1!"
1!
1I
0f
1w
0("
0F
1#
0L
0\
0U
1Z
0K
1c
1*
0G
1Y
0'
1$
0-
0=
06
1;
0,
1D
0(
1:
1%
#4400000
1/
18
0)
1.
13
0;
1+
0D
1(
0:
0%
#4500000
1N
1W
0H
1M
1R
0Z
1J
0c
0!
0*
1=
1G
0Y
0'"
1'
0.
0$
03
1<
0+
1A
0(
19
1%
#4600000
08
1)
0/
1-
16
0<
1,
0A
1(
09
0%
#4700000
0v
1g
0m
1k
1t
0z
1j
0!"
0I
1\
1f
0w
1F
0M
0#
0R
1[
0J
1`
1!
1*
0G
1X
1'"
0'
1$
0-
0=
06
1;
0,
1D
0(
1:
1%
#4800000
1/
18
0)
1.
13
0;
1+
0D
1(
0:
0%
#4900000
0W
1H
0N
1L
1U
0[
1K
0`
0!
0*
1=
1G
0X
0'"
1'
0.
0$
03
1<
0+
1A
0(
19
1%
#5000000
08
1)
0/
1-
16
0<
1,
0A
1(
09
0%
#5100000
1h
0&"
1("
0e
1"
0k
0{
0t
1y
0j
1$"
1I
0f
1x
0F
1#
0L
0\
0U
1Z
0K
1c
1!
1*
0G
1Y
0'"
0'
1$
0-
0=
06
1;
0,
1D
0(
1:
1%
#5200000
1/
18
0)
1.
13
0;
1+
0D
1(
0:
0%
#5300000
1N
1W
0H
1M
1R
0Z
1J
0c
0*
1=
1G
0Y
1'
0.
0$
03
1<
0+
1A
0(
19
1%
#5400000
08
1)
0/
1-
16
0<
1,
0A
1(
09
0%
#5500000
1m
1v
0g
1l
1q
0y
1i
0$"
0!
0I
1\
1f
0x
0("
1F
0M
0#
0R
1[
0J
1`
1*
0G
1X
0'
1$
0-
0=
06
1;
0,
1D
0(
1:
1%
#5600000
1/
18
0)
1.
13
0;
1+
0D
1(
0:
0%
#5700000
0W
1H
0N
1L
1U
0[
1K
0`
0*
1=
1G
0X
1'
0.
0$
03
1<
0+
1A
0(
19
1%
#5800000
08
1)
0/
1-
16
0<
1,
0A
1(
09
0%
#5900000
1'"
0h
1{
1&"
1e
0l
0"
0q
1z
0i
1!"
1!
1I
0f
1w
0("
0F
1#
0L
0\
0U
1Z
0K
1c
1*
0G
1Y
0'
1$
0-
0=
06
1;
0,
1D
0(
1:
1%
#6000000
1/
18
0)
1.
13
0;
1+
0D
1(
0:
0%
#6100000
1N
1W
0H
1M
1R
0Z
1J
0c
0!
0*
1=
1G
0Y
0'"
1'
0.
0$
03
1<
0+
1A
0(
19
1%
#6200000
08
1)
0/
1-
16
0<
1,
0A
1(
09
0%
#6300000
0v
1g
0m
1k
1t
0z
1j
0!"
0I
1\
1f
0w
1F
0M
0#
0R
1[
0J
1`
1!
1*
0G
1X
1'"
0'
1$
0-
0=
06
1;
0,
1D
0(
1:
1%
#6400000
1/
18
0)
1.
13
0;
1+
0D
1(
0:
0%
#6500000
0W
1H
0N
1L
1U
0[
1K
0`
0!
0*
1=
1G
0X
0'"
1'
0.
0$
03
1<
0+
1A
0(
19
1%
#6600000
08
1)
0/
1-
16
0<
1,
0A
1(
09
0%
#6700000
1h
0&"
1("
0e
1"
0k
0{
0t
1y
0j
1$"
1I
0f
1x
0F
1#
0L
0\
0U
1Z
0K
1c
1!
1*
0G
1Y
0'"
0'
1$
0-
0=
06
1;
0,
1D
0(
1:
1%
#6800000
1/
18
0)
1.
13
0;
1+
0D
1(
0:
0%
#6900000
1N
1W
0H
1M
1R
0Z
1J
0c
0*
1=
1G
0Y
1'
0.
0$
03
1<
0+
1A
0(
19
1%
#7000000
08
1)
0/
1-
16
0<
1,
0A
1(
09
0%
#7100000
1m
1v
0g
1l
1q
0y
1i
0$"
0!
0I
1\
1f
0x
0("
1F
0M
0#
0R
1[
0J
1`
1*
0G
1X
0'
1$
0-
0=
06
1;
0,
1D
0(
1:
1%
#7200000
1/
18
0)
1.
13
0;
1+
0D
1(
0:
0%
#7300000
0W
1H
0N
1L
1U
0[
1K
0`
0*
1=
1G
0X
1'
0.
0$
03
1<
0+
1A
0(
19
1%
#7400000
08
1)
0/
1-
16
0<
1,
0A
1(
09
0%
#7500000
1'"
0h
1{
1&"
1e
0l
0"
0q
1z
0i
1!"
1!
1I
0f
1w
0("
0F
1#
0L
0\
0U
1Z
0K
1c
1*
0G
1Y
0'
1$
0-
0=
06
1;
0,
1D
0(
1:
1%
#7600000
1/
18
0)
1.
13
0;
1+
0D
1(
0:
0%
#7700000
1N
1W
0H
1M
1R
0Z
1J
0c
0!
0*
1=
1G
0Y
0'"
1'
0.
0$
03
1<
0+
1A
0(
19
1%
#7800000
08
1)
0/
1-
16
0<
1,
0A
1(
09
0%
#7900000
0v
1g
0m
1k
1t
0z
1j
0!"
0I
1\
1f
0w
1F
0M
0#
0R
1[
0J
1`
1!
1*
0G
1X
1'"
0'
1$
0-
0=
06
1;
0,
1D
0(
1:
1%
#8000000
1/
18
0)
1.
13
0;
1+
0D
1(
0:
0%
#8100000
0W
1H
0N
1L
1U
0[
1K
0`
0!
0*
1=
1G
0X
0'"
1'
0.
0$
03
1<
0+
1A
0(
19
1%
#8200000
08
1)
0/
1-
16
0<
1,
0A
1(
09
0%
#8300000
1h
0&"
1("
0e
1"
0k
0{
0t
1y
0j
1$"
1I
0f
1x
0F
1#
0L
0\
0U
1Z
0K
1c
1!
1*
0G
1Y
0'"
0'
1$
0-
0=
06
1;
0,
1D
0(
1:
1%
#8400000
1/
18
0)
1.
13
0;
1+
0D
1(
0:
0%
#8500000
1N
1W
0H
1M
1R
0Z
1J
0c
0*
1=
1G
0Y
1'
0.
0$
03
1<
0+
1A
0(
19
1%
#8600000
08
1)
0/
1-
16
0<
1,
0A
1(
09
0%
#8700000
1m
1v
0g
1l
1q
0y
1i
0$"
0!
0I
1\
1f
0x
0("
1F
0M
0#
0R
1[
0J
1`
1*
0G
1X
0'
1$
0-
0=
06
1;
0,
1D
0(
1:
1%
#8800000
1/
18
0)
1.
13
0;
1+
0D
1(
0:
0%
#8900000
0W
1H
0N
1L
1U
0[
1K
0`
0*
1=
1G
0X
1'
0.
0$
03
1<
0+
1A
0(
19
1%
#9000000
08
1)
0/
1-
16
0<
1,
0A
1(
09
0%
#9100000
1'"
0h
1{
1&"
1e
0l
0"
0q
1z
0i
1!"
1!
1I
0f
1w
0("
0F
1#
0L
0\
0U
1Z
0K
1c
1*
0G
1Y
0'
1$
0-
0=
06
1;
0,
1D
0(
1:
1%
#9200000
1/
18
0)
1.
13
0;
1+
0D
1(
0:
0%
#9300000
1N
1W
0H
1M
1R
0Z
1J
0c
0!
0*
1=
1G
0Y
0'"
1'
0.
0$
03
1<
0+
1A
0(
19
1%
#9400000
08
1)
0/
1-
16
0<
1,
0A
1(
09
0%
#9500000
0v
1g
0m
1k
1t
0z
1j
0!"
0I
1\
1f
0w
1F
0M
0#
0R
1[
0J
1`
1!
1*
0G
1X
1'"
0'
1$
0-
0=
06
1;
0,
1D
0(
1:
1%
#9600000
1/
18
0)
1.
13
0;
1+
0D
1(
0:
0%
#9700000
0W
1H
0N
1L
1U
0[
1K
0`
0!
0*
1=
1G
0X
0'"
1'
0.
0$
03
1<
0+
1A
0(
19
1%
#9800000
08
1)
0/
1-
16
0<
1,
0A
1(
09
0%
#9900000
1h
0&"
1("
0e
1"
0k
0{
0t
1y
0j
1$"
1I
0f
1x
0F
1#
0L
0\
0U
1Z
0K
1c
1!
1*
0G
1Y
0'"
0'
1$
0-
0=
06
1;
0,
1D
0(
1:
1%
#10000000
1/
18
0)
1.
13
0;
1+
0D
1(
0:
0%
#10100000
1N
1W
0H
1M
1R
0Z
1J
0c
0*
1=
1G
0Y
1'
0.
0$
03
1<
0+
1A
0(
19
1%
#10200000
08
1)
0/
1-
16
0<
1,
0A
1(
09
0%
#10300000
1m
1v
0g
1l
1q
0y
1i
0$"
0!
0I
1\
1f
0x
0("
1F
0M
0#
0R
1[
0J
1`
1*
0G
1X
0'
1$
0-
0=
06
1;
0,
1D
0(
1:
1%
#10400000
1/
18
0)
1.
13
0;
1+
0D
1(
0:
0%
#10500000
0W
1H
0N
1L
1U
0[
1K
0`
0*
1=
1G
0X
1'
0.
0$
03
1<
0+
1A
0(
19
1%
#10600000
08
1)
0/
1-
16
0<
1,
0A
1(
09
0%
#10700000
1'"
0h
1{
1&"
1e
0l
0"
0q
1z
0i
1!"
1!
1I
0f
1w
0("
0F
1#
0L
0\
0U
1Z
0K
1c
1*
0G
1Y
0'
1$
0-
0=
06
1;
0,
1D
0(
1:
1%
#10800000
1/
18
0)
1.
13
0;
1+
0D
1(
0:
0%
#10900000
1N
1W
0H
1M
1R
0Z
1J
0c
0!
0*
1=
1G
0Y
0'"
1'
0.
0$
03
1<
0+
1A
0(
19
1%
#11000000
08
1)
0/
1-
16
0<
1,
0A
1(
09
0%
#11100000
0v
1g
0m
1k
1t
0z
1j
0!"
0I
1\
1f
0w
1F
0M
0#
0R
1[
0J
1`
1!
1*
0G
1X
1'"
0'
1$
0-
0=
06
1;
0,
1D
0(
1:
1%
#11200000
1/
18
0)
1.
13
0;
1+
0D
1(
0:
0%
#11300000
0W
1H
0N
1L
1U
0[
1K
0`
0!
0*
1=
1G
0X
0'"
1'
0.
0$
03
1<
0+
1A
0(
19
1%
#11400000
08
1)
0/
1-
16
0<
1,
0A
1(
09
0%
#11500000
1h
0&"
1("
0e
1"
0k
0{
0t
1y
0j
1$"
1I
0f
1x
0F
1#
0L
0\
0U
1Z
0K
1c
1!
1*
0G
1Y
0'"
0'
1$
0-
0=
06
1;
0,
1D
0(
1:
1%
#11600000
1/
18
0)
1.
13
0;
1+
0D
1(
0:
0%
#11700000
1N
1W
0H
1M
1R
0Z
1J
0c
0*
1=
1G
0Y
1'
0.
0$
03
1<
0+
1A
0(
19
1%
#11800000
08
1)
0/
1-
16
0<
1,
0A
1(
09
0%
#11900000
1m
1v
0g
1l
1q
0y
1i
0$"
0!
0I
1\
1f
0x
0("
1F
0M
0#
0R
1[
0J
1`
1*
0G
1X
0'
1$
0-
0=
06
1;
0,
1D
0(
1:
1%
#12000000
1/
18
0)
1.
13
0;
1+
0D
1(
0:
0%
#12100000
0W
1H
0N
1L
1U
0[
1K
0`
0*
1=
1G
0X
1'
0.
0$
03
1<
0+
1A
0(
19
1%
#12200000
08
1)
0/
1-
16
0<
1,
0A
1(
09
0%
#12300000
1'"
0h
1{
1&"
1e
0l
0"
0q
1z
0i
1!"
1!
1I
0f
1w
0("
0F
1#
0L
0\
0U
1Z
0K
1c
1*
0G
1Y
0'
1$
0-
0=
06
1;
0,
1D
0(
1:
1%
#12400000
1/
18
0)
1.
13
0;
1+
0D
1(
0:
0%
#12500000
1N
1W
0H
1M
1R
0Z
1J
0c
0!
0*
1=
1G
0Y
0'"
1'
0.
0$
03
1<
0+
1A
0(
19
1%
#12600000
08
1)
0/
1-
16
0<
1,
0A
1(
09
0%
#12700000
0v
1g
0m
1k
1t
0z
1j
0!"
0I
1\
1f
0w
1F
0M
0#
0R
1[
0J
1`
1!
1*
0G
1X
1'"
0'
1$
0-
0=
06
1;
0,
1D
0(
1:
1%
#12800000
1/
18
0)
1.
13
0;
1+
0D
1(
0:
0%
#12900000
0W
1H
0N
1L
1U
0[
1K
0`
0!
0*
1=
1G
0X
0'"
1'
0.
0$
03
1<
0+
1A
0(
19
1%
#13000000
08
1)
0/
1-
16
0<
1,
0A
1(
09
0%
#13100000
1h
0&"
1("
0e
1"
0k
0{
0t
1y
0j
1$"
1I
0f
1x
0F
1#
0L
0\
0U
1Z
0K
1c
1!
1*
0G
1Y
0'"
0'
1$
0-
0=
06
1;
0,
1D
0(
1:
1%
#13200000
1/
18
0)
1.
13
0;
1+
0D
1(
0:
0%
#13300000
1N
1W
0H
1M
1R
0Z
1J
0c
0*
1=
1G
0Y
1'
0.
0$
03
1<
0+
1A
0(
19
1%
#13400000
08
1)
0/
1-
16
0<
1,
0A
1(
09
0%
#13500000
1m
1v
0g
1l
1q
0y
1i
0$"
0!
0I
1\
1f
0x
0("
1F
0M
0#
0R
1[
0J
1`
1*
0G
1X
0'
1$
0-
0=
06
1;
0,
1D
0(
1:
1%
#13600000
1/
18
0)
1.
13
0;
1+
0D
1(
0:
0%
#13700000
0W
1H
0N
1L
1U
0[
1K
0`
0*
1=
1G
0X
1'
0.
0$
03
1<
0+
1A
0(
19
1%
#13800000
08
1)
0/
1-
16
0<
1,
0A
1(
09
0%
#13900000
1'"
0h
1{
1&"
1e
0l
0"
0q
1z
0i
1!"
1!
1I
0f
1w
0("
0F
1#
0L
0\
0U
1Z
0K
1c
1*
0G
1Y
0'
1$
0-
0=
06
1;
0,
1D
0(
1:
1%
#14000000
1/
18
0)
1.
13
0;
1+
0D
1(
0:
0%
#14100000
1N
1W
0H
1M
1R
0Z
1J
0c
0!
0*
1=
1G
0Y
0'"
1'
0.
0$
03
1<
0+
1A
0(
19
1%
#14200000
08
1)
0/
1-
16
0<
1,
0A
1(
09
0%
#14300000
0v
1g
0m
1k
1t
0z
1j
0!"
0I
1\
1f
0w
1F
0M
0#
0R
1[
0J
1`
1!
1*
0G
1X
1'"
0'
1$
0-
0=
06
1;
0,
1D
0(
1:
1%
#14400000
1/
18
0)
1.
13
0;
1+
0D
1(
0:
0%
#14500000
0W
1H
0N
1L
1U
0[
1K
0`
0!
0*
1=
1G
0X
0'"
1'
0.
0$
03
1<
0+
1A
0(
19
1%
#14600000
08
1)
0/
1-
16
0<
1,
0A
1(
09
0%
#14700000
1h
0&"
1("
0e
1"
0k
0{
0t
1y
0j
1$"
1I
0f
1x
0F
1#
0L
0\
0U
1Z
0K
1c
1!
1*
0G
1Y
0'"
0'
1$
0-
0=
06
1;
0,
1D
0(
1:
1%
#14800000
1/
18
0)
1.
13
0;
1+
0D
1(
0:
0%
#14900000
1N
1W
0H
1M
1R
0Z
1J
0c
0*
1=
1G
0Y
1'
0.
0$
03
1<
0+
1A
0(
19
1%
#15000000
08
1)
0/
1-
16
0<
1,
0A
1(
09
0%
#15100000
1m
1v
0g
1l
1q
0y
1i
0$"
0!
0I
1\
1f
0x
0("
1F
0M
0#
0R
1[
0J
1`
1*
0G
1X
0'
1$
0-
0=
06
1;
0,
1D
0(
1:
1%
#15200000
1/
18
0)
1.
13
0;
1+
0D
1(
0:
0%
